observed_string/__init__.py
observed_string/observed_string.py
observed_string/observed_string_ov.py
observed_string_8b1-0.1.dist-info/METADATA
observed_string_8b1-0.1.dist-info/WHEEL
observed_string_8b1-0.1.dist-info/top_level.txt
observed_string_8b1-0.1.dist-info/RECORD
