Metadata-Version: 2.1
Name: observed-string-8b1
Version: 0.1
Summary: Implementation of python API for the extension to the STIX 2.1 observed string
Requires-Dist: stix2
Provides-Extra: dev
Requires-Dist: pytest ; extra == 'dev'
Requires-Dist: tox ; extra == 'dev'
